earthquake_latest/__init__.py
earthquake_latest_indonesia-0.0.2.dist-info/LICENSE
earthquake_latest_indonesia-0.0.2.dist-info/METADATA
earthquake_latest_indonesia-0.0.2.dist-info/WHEEL
earthquake_latest_indonesia-0.0.2.dist-info/top_level.txt
earthquake_latest_indonesia-0.0.2.dist-info/RECORD
