Metadata-Version: 2.1
Name: earthquake-latest-indonesia
Version: 0.0.2
Summary: A small package earthquake latest indonesia
Author-email: FSI <paijo2012@gmail.com>
License: GNU GENERAL PUBLIC LICENSE
Project-URL: Homepage, https://github.com/farissahaluddin/earthquake-detection
Project-URL: Bug Tracker, https://github.com/farissahaluddin/earthquake-detection/issues
Classifier: Programming Language :: Python :: 3
Classifier: License :: OSI Approved :: MIT License
Classifier: Operating System :: OS Independent
Requires-Python: >=3.7
License-File: LICENSE
